tg_qso_bot/__init__.py
tg_qso_bot/bot/__init__.py
tg_qso_bot/bot/__main__.py
tg_qso_bot/bot/app.py
tg_qso_bot/bot/errors_handling.py
tg_qso_bot/bot/handlers/__init__.py
tg_qso_bot/bot/handlers/delete_messages.py
tg_qso_bot/bot/handlers/request_qso.py
tg_qso_bot/bot/messages_log.py
tg_qso_bot/bot/messages_watchdog.py
tg_qso_bot/models/__init__.py
tg_qso_bot/models/qso.py
tg_qso_bot/qso_sources/__init__.py
tg_qso_bot/qso_sources/exceptions.py
tg_qso_bot/qso_sources/hamlog.py
tg_qso_bot/qso_sources/source.py
tg_qso_bot/utils/logging.py
tg_qso_bot-1.3.2.dist-info/entry_points.txt
tg_qso_bot-1.3.2.dist-info/LICENSE
tg_qso_bot-1.3.2.dist-info/WHEEL
tg_qso_bot-1.3.2.dist-info/METADATA
tg_qso_bot-1.3.2.dist-info/RECORD
