Metadata-Version: 2.1
Name: tg-qso-bot
Version: 1.3.2
Summary: Simple HAM helper bot written on Python
Home-page: https://github.com/exepirit/tg-qso-bot
License: MIT
Author: exepirit
Author-email: you@example.com
Requires-Python: >=3.8,<4.0
Classifier: License :: OSI Approved :: MIT License
Classifier: Programming Language :: Python :: 3
Classifier: Programming Language :: Python :: 3.10
Classifier: Programming Language :: Python :: 3.8
Classifier: Programming Language :: Python :: 3.9
Requires-Dist: Pyrogram (>=1.2.9,<2.0.0)
Requires-Dist: beautifulsoup4 (>=4.9.1,<5.0.0)
Requires-Dist: dynaconf (>=2.2.3,<3.0.0)
Requires-Dist: requests (>=2.23.0,<3.0.0)
Requires-Dist: sentry-sdk (>=0.19.5,<0.20.0)
Project-URL: Repository, https://github.com/exepirit/tg-qso-bot
